{"metadata": {"dbt_schema_version": "https://schemas.getdbt.com/dbt/run-results/v1.json", "dbt_version": "0.19.0", "generated_at": "2021-08-19T16:05:00.747527Z", "invocation_id": "17338a7a-ea3b-43df-8a80-9d9e0977654b", "env": {}}, "results": [{"status": "success", "timing": [{"name": "compile", "started_at": "2021-08-19T16:04:50.983589Z", "completed_at": "2021-08-19T16:04:51.030101Z"}, {"name": "execute", "started_at": "2021-08-19T16:04:51.030856Z", "completed_at": "2021-08-19T16:04:51.030873Z"}], "thread_id": "Thread-1", "execution_time": 0.04946494102478027, "message": null, "adapter_response": {}, "unique_id": "seed.snowplow_web_integration_tests.snowplow_web_events"}, {"status": "success", "timing": [{"name": "compile", "started_at": "2021-08-19T16:04:50.983864Z", "completed_at": "2021-08-19T16:04:51.030610Z"}, {"name": "execute", "started_at": "2021-08-19T16:04:51.031068Z", "completed_at": "2021-08-19T16:04:51.031074Z"}], "thread_id": "Thread-3", "execution_time": 0.04880690574645996, "message": null, "adapter_response": {}, "unique_id": "seed.snowplow_web_integration_tests.snowplow_web_page_views_expected"}, {"status": "success", "timing": [{"name": "compile", "started_at": "2021-08-19T16:04:50.983734Z", "completed_at": "2021-08-19T16:04:51.034477Z"}, {"name": "execute", "started_at": "2021-08-19T16:04:51.035420Z", "completed_at": "2021-08-19T16:04:51.035426Z"}], "thread_id": "Thread-2", "execution_time": 0.05360007286071777, "message": null, "adapter_response": {}, "unique_id": "model.snowplow_web.snowplow_web_base_new_event_limits"}, {"status": "success", "timing": [{"name": "compile", "started_at": "2021-08-19T16:04:50.983981Z", "completed_at": "2021-08-19T16:04:51.035040Z"}, {"name": "execute", "started_at": "2021-08-19T16:04:51.035753Z", "completed_at": "2021-08-19T16:04:51.035758Z"}], "thread_id": "Thread-4", "execution_time": 0.053031206130981445, "message": null, "adapter_response": {}, "unique_id": "seed.snowplow_web_integration_tests.snowplow_web_sessions_expected"}, {"status": "success", "timing": [{"name": "compile", "started_at": "2021-08-19T16:04:51.035900Z", "completed_at": "2021-08-19T16:04:51.048962Z"}, {"name": "execute", "started_at": "2021-08-19T16:04:51.049579Z", "completed_at": "2021-08-19T16:04:51.049584Z"}], "thread_id": "Thread-1", "execution_time": 0.01474905014038086, "message": null, "adapter_response": {}, "unique_id": "seed.snowplow_web_integration_tests.snowplow_web_users_expected"}, {"status": "success", "timing": [{"name": "compile", "started_at": "2021-08-19T16:04:51.036120Z", "completed_at": "2021-08-19T16:04:51.049311Z"}, {"name": "execute", "started_at": "2021-08-19T16:04:51.049750Z", "completed_at": "2021-08-19T16:04:51.049753Z"}], "thread_id": "Thread-3", "execution_time": 0.01940298080444336, "message": null, "adapter_response": {}, "unique_id": "operation.snowplow_web.snowplow_web-on-run-start-0"}, {"status": "success", "timing": [{"name": "compile", "started_at": "2021-08-19T16:04:51.049858Z", "completed_at": "2021-08-19T16:04:51.060350Z"}, {"name": "execute", "started_at": "2021-08-19T16:04:51.060609Z", "completed_at": "2021-08-19T16:04:51.060615Z"}], "thread_id": "Thread-4", "execution_time": 0.019569873809814453, "message": null, "adapter_response": {}, "unique_id": "model.snowplow_web_integration_tests.snowplow_web_page_views_expected_stg"}, {"status": "success", "timing": [{"name": "compile", "started_at": "2021-08-19T16:04:51.049700Z", "completed_at": "2021-08-19T16:04:51.060712Z"}, {"name": "execute", "started_at": "2021-08-19T16:04:51.069086Z", "completed_at": "2021-08-19T16:04:51.069091Z"}], "thread_id": "Thread-2", "execution_time": 0.02034902572631836, "message": null, "adapter_response": {}, "unique_id": "model.snowplow_web_integration_tests.snowplow_web_events_stg"}, {"status": "success", "timing": [{"name": "compile", "started_at": "2021-08-19T16:04:51.060544Z", "completed_at": "2021-08-19T16:04:51.069782Z"}, {"name": "execute", "started_at": "2021-08-19T16:04:51.070100Z", "completed_at": "2021-08-19T16:04:51.070104Z"}], "thread_id": "Thread-3", "execution_time": 0.010333061218261719, "message": null, "adapter_response": {}, "unique_id": "model.snowplow_web_integration_tests.snowplow_web_users_expected_stg"}, {"status": "success", "timing": [{"name": "compile", "started_at": "2021-08-19T16:04:51.060490Z", "completed_at": "2021-08-19T16:04:51.069881Z"}, {"name": "execute", "started_at": "2021-08-19T16:04:51.070213Z", "completed_at": "2021-08-19T16:04:51.070217Z"}], "thread_id": "Thread-1", "execution_time": 0.01062774658203125, "message": null, "adapter_response": {}, "unique_id": "model.snowplow_web_integration_tests.snowplow_web_sessions_expected_stg"}, {"status": "success", "timing": [{"name": "compile", "started_at": "2021-08-19T16:04:51.070333Z", "completed_at": "2021-08-19T16:04:53.248136Z"}, {"name": "execute", "started_at": "2021-08-19T16:04:53.248526Z", "completed_at": "2021-08-19T16:04:53.248540Z"}], "thread_id": "Thread-4", "execution_time": 2.178838014602661, "message": null, "adapter_response": {}, "unique_id": "model.snowplow_web.snowplow_web_base_sessions_lifecycle_manifest"}, {"status": "success", "timing": [{"name": "compile", "started_at": "2021-08-19T16:04:53.259163Z", "completed_at": "2021-08-19T16:04:53.274312Z"}, {"name": "execute", "started_at": "2021-08-19T16:04:53.274511Z", "completed_at": "2021-08-19T16:04:53.274520Z"}], "thread_id": "Thread-3", "execution_time": 0.01876997947692871, "message": null, "adapter_response": {}, "unique_id": "test.snowplow_web.not_null_snowplow_web_base_sessions_lifecycle_manifest_session_id"}, {"status": "success", "timing": [{"name": "compile", "started_at": "2021-08-19T16:04:53.259280Z", "completed_at": "2021-08-19T16:04:53.274815Z"}, {"name": "execute", "started_at": "2021-08-19T16:04:53.275079Z", "completed_at": "2021-08-19T16:04:53.275084Z"}], "thread_id": "Thread-1", "execution_time": 0.016316890716552734, "message": null, "adapter_response": {}, "unique_id": "test.snowplow_web.unique_snowplow_web_base_sessions_lifecycle_manifest_session_id"}, {"status": "success", "timing": [{"name": "compile", "started_at": "2021-08-19T16:04:53.249675Z", "completed_at": "2021-08-19T16:04:54.595272Z"}, {"name": "execute", "started_at": "2021-08-19T16:04:54.595714Z", "completed_at": "2021-08-19T16:04:54.595732Z"}], "thread_id": "Thread-2", "execution_time": 1.3468811511993408, "message": null, "adapter_response": {}, "unique_id": "model.snowplow_web.snowplow_web_base_sessions_this_run"}, {"status": "success", "timing": [{"name": "compile", "started_at": "2021-08-19T16:04:54.617125Z", "completed_at": "2021-08-19T16:04:54.661400Z"}, {"name": "execute", "started_at": "2021-08-19T16:04:54.661756Z", "completed_at": "2021-08-19T16:04:54.661763Z"}], "thread_id": "Thread-1", "execution_time": 0.06296396255493164, "message": null, "adapter_response": {}, "unique_id": "test.snowplow_web.not_null_snowplow_web_base_sessions_this_run_session_id"}, {"status": "success", "timing": [{"name": "compile", "started_at": "2021-08-19T16:04:54.634844Z", "completed_at": "2021-08-19T16:04:54.661546Z"}, {"name": "execute", "started_at": "2021-08-19T16:04:54.661994Z", "completed_at": "2021-08-19T16:04:54.661998Z"}], "thread_id": "Thread-2", "execution_time": 0.06301641464233398, "message": null, "adapter_response": {}, "unique_id": "test.snowplow_web.unique_snowplow_web_base_sessions_this_run_session_id"}, {"status": "success", "timing": [{"name": "compile", "started_at": "2021-08-19T16:04:54.599965Z", "completed_at": "2021-08-19T16:04:54.661869Z"}, {"name": "execute", "started_at": "2021-08-19T16:04:54.662400Z", "completed_at": "2021-08-19T16:04:54.662405Z"}], "thread_id": "Thread-3", "execution_time": 0.070404052734375, "message": null, "adapter_response": {}, "unique_id": "model.snowplow_web.snowplow_web_users_userids_this_run"}, {"status": "success", "timing": [{"name": "compile", "started_at": "2021-08-19T16:04:54.678141Z", "completed_at": "2021-08-19T16:04:54.687712Z"}, {"name": "execute", "started_at": "2021-08-19T16:04:54.687844Z", "completed_at": "2021-08-19T16:04:54.687850Z"}], "thread_id": "Thread-2", "execution_time": 0.010128974914550781, "message": null, "adapter_response": {}, "unique_id": "test.snowplow_web.unique_snowplow_web_users_userids_this_run_domain_userid"}, {"status": "success", "timing": [{"name": "compile", "started_at": "2021-08-19T16:04:54.678081Z", "completed_at": "2021-08-19T16:04:54.688168Z"}, {"name": "execute", "started_at": "2021-08-19T16:04:54.688280Z", "completed_at": "2021-08-19T16:04:54.688283Z"}], "thread_id": "Thread-1", "execution_time": 0.010816097259521484, "message": null, "adapter_response": {}, "unique_id": "test.snowplow_web.not_null_snowplow_web_users_userids_this_run_domain_userid"}, {"status": "success", "timing": [{"name": "compile", "started_at": "2021-08-19T16:04:54.599125Z", "completed_at": "2021-08-19T16:04:55.891124Z"}, {"name": "execute", "started_at": "2021-08-19T16:04:55.891537Z", "completed_at": "2021-08-19T16:04:55.891558Z"}], "thread_id": "Thread-4", "execution_time": 1.2940542697906494, "message": null, "adapter_response": {}, "unique_id": "model.snowplow_web.snowplow_web_base_events_this_run"}, {"status": "success", "timing": [{"name": "compile", "started_at": "2021-08-19T16:04:55.894847Z", "completed_at": "2021-08-19T16:04:55.936597Z"}, {"name": "execute", "started_at": "2021-08-19T16:04:55.938540Z", "completed_at": "2021-08-19T16:04:55.938548Z"}], "thread_id": "Thread-3", "execution_time": 0.04540729522705078, "message": null, "adapter_response": {}, "unique_id": "model.snowplow_web.snowplow_web_pv_engaged_time"}, {"status": "success", "timing": [{"name": "compile", "started_at": "2021-08-19T16:04:55.908293Z", "completed_at": "2021-08-19T16:04:55.938740Z"}, {"name": "execute", "started_at": "2021-08-19T16:04:55.939291Z", "completed_at": "2021-08-19T16:04:55.939296Z"}], "thread_id": "Thread-1", "execution_time": 0.045117855072021484, "message": null, "adapter_response": {}, "unique_id": "operation.snowplow_web.snowplow_web-on-run-end-0"}, {"status": "success", "timing": [{"name": "compile", "started_at": "2021-08-19T16:04:55.909488Z", "completed_at": "2021-08-19T16:04:55.938901Z"}, {"name": "execute", "started_at": "2021-08-19T16:04:55.939464Z", "completed_at": "2021-08-19T16:04:55.939469Z"}], "thread_id": "Thread-4", "execution_time": 0.04501509666442871, "message": null, "adapter_response": {}, "unique_id": "test.snowplow_web.not_null_snowplow_web_base_events_this_run_event_id"}, {"status": "success", "timing": [{"name": "compile", "started_at": "2021-08-19T16:04:55.895572Z", "completed_at": "2021-08-19T16:04:55.939610Z"}, {"name": "execute", "started_at": "2021-08-19T16:04:55.940380Z", "completed_at": "2021-08-19T16:04:55.940385Z"}], "thread_id": "Thread-2", "execution_time": 0.04667925834655762, "message": null, "adapter_response": {}, "unique_id": "model.snowplow_web.snowplow_web_pv_scroll_depth"}, {"status": "success", "timing": [{"name": "compile", "started_at": "2021-08-19T16:04:55.941212Z", "completed_at": "2021-08-19T16:04:55.958869Z"}, {"name": "execute", "started_at": "2021-08-19T16:04:55.990002Z", "completed_at": "2021-08-19T16:04:55.990010Z"}], "thread_id": "Thread-3", "execution_time": 0.05022621154785156, "message": null, "adapter_response": {}, "unique_id": "test.snowplow_web.unique_snowplow_web_base_events_this_run_event_id"}, {"status": "success", "timing": [{"name": "compile", "started_at": "2021-08-19T16:04:55.947768Z", "completed_at": "2021-08-19T16:04:55.989818Z"}, {"name": "execute", "started_at": "2021-08-19T16:04:55.990552Z", "completed_at": "2021-08-19T16:04:55.990556Z"}], "thread_id": "Thread-1", "execution_time": 0.04977607727050781, "message": null, "adapter_response": {}, "unique_id": "test.snowplow_web.not_null_snowplow_web_pv_engaged_time_page_view_id"}, {"status": "success", "timing": [{"name": "compile", "started_at": "2021-08-19T16:04:55.947824Z", "completed_at": "2021-08-19T16:04:55.990431Z"}, {"name": "execute", "started_at": "2021-08-19T16:04:55.990870Z", "completed_at": "2021-08-19T16:04:55.990873Z"}], "thread_id": "Thread-4", "execution_time": 0.04990100860595703, "message": null, "adapter_response": {}, "unique_id": "test.snowplow_web.unique_snowplow_web_pv_engaged_time_page_view_id"}, {"status": "success", "timing": [{"name": "compile", "started_at": "2021-08-19T16:04:55.958811Z", "completed_at": "2021-08-19T16:04:55.991867Z"}, {"name": "execute", "started_at": "2021-08-19T16:04:55.992067Z", "completed_at": "2021-08-19T16:04:55.992070Z"}], "thread_id": "Thread-2", "execution_time": 0.05292105674743652, "message": null, "adapter_response": {}, "unique_id": "model.snowplow_web.snowplow_web_page_views_this_run"}, {"status": "success", "timing": [{"name": "compile", "started_at": "2021-08-19T16:04:55.992021Z", "completed_at": "2021-08-19T16:04:56.001549Z"}, {"name": "execute", "started_at": "2021-08-19T16:04:56.001992Z", "completed_at": "2021-08-19T16:04:56.001997Z"}], "thread_id": "Thread-1", "execution_time": 0.010577201843261719, "message": null, "adapter_response": {}, "unique_id": "test.snowplow_web.unique_snowplow_web_pv_scroll_depth_page_view_id"}, {"status": "success", "timing": [{"name": "compile", "started_at": "2021-08-19T16:04:55.991975Z", "completed_at": "2021-08-19T16:04:56.001782Z"}, {"name": "execute", "started_at": "2021-08-19T16:04:56.002143Z", "completed_at": "2021-08-19T16:04:56.002146Z"}], "thread_id": "Thread-3", "execution_time": 0.015765905380249023, "message": null, "adapter_response": {}, "unique_id": "test.snowplow_web.not_null_snowplow_web_pv_scroll_depth_page_view_id"}, {"status": "success", "timing": [{"name": "compile", "started_at": "2021-08-19T16:04:56.002095Z", "completed_at": "2021-08-19T16:04:56.031115Z"}, {"name": "execute", "started_at": "2021-08-19T16:04:56.031502Z", "completed_at": "2021-08-19T16:04:56.031507Z"}], "thread_id": "Thread-4", "execution_time": 0.03501582145690918, "message": null, "adapter_response": {}, "unique_id": "model.snowplow_web.snowplow_web_sessions_aggs"}, {"status": "success", "timing": [{"name": "compile", "started_at": "2021-08-19T16:04:56.031440Z", "completed_at": "2021-08-19T16:04:56.046408Z"}, {"name": "execute", "started_at": "2021-08-19T16:04:56.046586Z", "completed_at": "2021-08-19T16:04:56.046591Z"}], "thread_id": "Thread-1", "execution_time": 0.016065120697021484, "message": null, "adapter_response": {}, "unique_id": "test.snowplow_web.not_null_snowplow_web_page_views_this_run_absolute_time_in_s"}, {"status": "success", "timing": [{"name": "compile", "started_at": "2021-08-19T16:04:56.031640Z", "completed_at": "2021-08-19T16:04:56.046689Z"}, {"name": "execute", "started_at": "2021-08-19T16:04:56.047085Z", "completed_at": "2021-08-19T16:04:56.047089Z"}], "thread_id": "Thread-3", "execution_time": 0.016265153884887695, "message": null, "adapter_response": {}, "unique_id": "test.snowplow_web.not_null_snowplow_web_page_views_this_run_collector_tstamp"}, {"status": "success", "timing": [{"name": "compile", "started_at": "2021-08-19T16:04:56.041472Z", "completed_at": "2021-08-19T16:04:56.046789Z"}, {"name": "execute", "started_at": "2021-08-19T16:04:56.047193Z", "completed_at": "2021-08-19T16:04:56.047197Z"}], "thread_id": "Thread-4", "execution_time": 0.00632476806640625, "message": null, "adapter_response": {}, "unique_id": "test.snowplow_web.not_null_snowplow_web_page_views_this_run_derived_tstamp"}, {"status": "success", "timing": [{"name": "compile", "started_at": "2021-08-19T16:04:56.048054Z", "completed_at": "2021-08-19T16:04:56.061858Z"}, {"name": "execute", "started_at": "2021-08-19T16:04:56.061971Z", "completed_at": "2021-08-19T16:04:56.061976Z"}], "thread_id": "Thread-1", "execution_time": 0.014438867568969727, "message": null, "adapter_response": {}, "unique_id": "test.snowplow_web.not_null_snowplow_web_page_views_this_run_domain_sessionid"}, {"status": "success", "timing": [{"name": "compile", "started_at": "2021-08-19T16:04:56.052790Z", "completed_at": "2021-08-19T16:04:56.067940Z"}, {"name": "execute", "started_at": "2021-08-19T16:04:56.068084Z", "completed_at": "2021-08-19T16:04:56.068089Z"}], "thread_id": "Thread-3", "execution_time": 0.02038097381591797, "message": null, "adapter_response": {}, "unique_id": "test.snowplow_web.not_null_snowplow_web_page_views_this_run_domain_sessionidx"}, {"status": "success", "timing": [{"name": "compile", "started_at": "2021-08-19T16:04:56.053168Z", "completed_at": "2021-08-19T16:04:56.068205Z"}, {"name": "execute", "started_at": "2021-08-19T16:04:56.068570Z", "completed_at": "2021-08-19T16:04:56.068574Z"}], "thread_id": "Thread-4", "execution_time": 0.020762920379638672, "message": null, "adapter_response": {}, "unique_id": "test.snowplow_web.not_null_snowplow_web_page_views_this_run_domain_userid"}, {"status": "success", "timing": [{"name": "compile", "started_at": "2021-08-19T16:04:56.062593Z", "completed_at": "2021-08-19T16:04:56.068671Z"}, {"name": "execute", "started_at": "2021-08-19T16:04:56.069073Z", "completed_at": "2021-08-19T16:04:56.069077Z"}], "thread_id": "Thread-1", "execution_time": 0.007030010223388672, "message": null, "adapter_response": {}, "unique_id": "test.snowplow_web.not_null_snowplow_web_page_views_this_run_dvce_created_tstamp"}, {"status": "success", "timing": [{"name": "compile", "started_at": "2021-08-19T16:04:56.069570Z", "completed_at": "2021-08-19T16:04:56.083178Z"}, {"name": "execute", "started_at": "2021-08-19T16:04:56.083331Z", "completed_at": "2021-08-19T16:04:56.083336Z"}], "thread_id": "Thread-3", "execution_time": 0.014335393905639648, "message": null, "adapter_response": {}, "unique_id": "test.snowplow_web.not_null_snowplow_web_page_views_this_run_end_tstamp"}, {"status": "success", "timing": [{"name": "compile", "started_at": "2021-08-19T16:04:56.074186Z", "completed_at": "2021-08-19T16:04:56.083692Z"}, {"name": "execute", "started_at": "2021-08-19T16:04:56.084093Z", "completed_at": "2021-08-19T16:04:56.084097Z"}], "thread_id": "Thread-4", "execution_time": 0.014782190322875977, "message": null, "adapter_response": {}, "unique_id": "test.snowplow_web.not_null_snowplow_web_page_views_this_run_engaged_time_in_s"}, {"status": "success", "timing": [{"name": "compile", "started_at": "2021-08-19T16:04:56.078727Z", "completed_at": "2021-08-19T16:04:56.083988Z"}, {"name": "execute", "started_at": "2021-08-19T16:04:56.084237Z", "completed_at": "2021-08-19T16:04:56.084240Z"}], "thread_id": "Thread-1", "execution_time": 0.01455998420715332, "message": null, "adapter_response": {}, "unique_id": "test.snowplow_web.not_null_snowplow_web_page_views_this_run_event_id"}, {"status": "success", "timing": [{"name": "compile", "started_at": "2021-08-19T16:04:56.084191Z", "completed_at": "2021-08-19T16:04:56.089422Z"}, {"name": "execute", "started_at": "2021-08-19T16:04:56.089631Z", "completed_at": "2021-08-19T16:04:56.089635Z"}], "thread_id": "Thread-3", "execution_time": 0.014495134353637695, "message": null, "adapter_response": {}, "unique_id": "test.snowplow_web.not_null_snowplow_web_page_views_this_run_network_userid"}, {"status": "success", "timing": [{"name": "compile", "started_at": "2021-08-19T16:04:56.089533Z", "completed_at": "2021-08-19T16:04:56.103970Z"}, {"name": "execute", "started_at": "2021-08-19T16:04:56.104453Z", "completed_at": "2021-08-19T16:04:56.104458Z"}], "thread_id": "Thread-4", "execution_time": 0.01572108268737793, "message": null, "adapter_response": {}, "unique_id": "test.snowplow_web.not_null_snowplow_web_page_views_this_run_page_url"}, {"status": "success", "timing": [{"name": "compile", "started_at": "2021-08-19T16:04:56.089581Z", "completed_at": "2021-08-19T16:04:56.104147Z"}, {"name": "execute", "started_at": "2021-08-19T16:04:56.104609Z", "completed_at": "2021-08-19T16:04:56.104612Z"}], "thread_id": "Thread-1", "execution_time": 0.015720844268798828, "message": null, "adapter_response": {}, "unique_id": "test.snowplow_web.not_null_snowplow_web_page_views_this_run_page_view_id"}, {"status": "success", "timing": [{"name": "compile", "started_at": "2021-08-19T16:04:56.098895Z", "completed_at": "2021-08-19T16:04:56.104257Z"}, {"name": "execute", "started_at": "2021-08-19T16:04:56.104711Z", "completed_at": "2021-08-19T16:04:56.104714Z"}], "thread_id": "Thread-3", "execution_time": 0.006396055221557617, "message": null, "adapter_response": {}, "unique_id": "test.snowplow_web.not_null_snowplow_web_page_views_this_run_page_view_in_session_index"}, {"status": "success", "timing": [{"name": "compile", "started_at": "2021-08-19T16:04:56.105922Z", "completed_at": "2021-08-19T16:04:56.119567Z"}, {"name": "execute", "started_at": "2021-08-19T16:04:56.119707Z", "completed_at": "2021-08-19T16:04:56.119713Z"}], "thread_id": "Thread-4", "execution_time": 0.014478921890258789, "message": null, "adapter_response": {}, "unique_id": "test.snowplow_web.not_null_snowplow_web_page_views_this_run_page_views_in_session"}, {"status": "success", "timing": [{"name": "compile", "started_at": "2021-08-19T16:04:56.105968Z", "completed_at": "2021-08-19T16:04:56.119829Z"}, {"name": "execute", "started_at": "2021-08-19T16:04:56.120134Z", "completed_at": "2021-08-19T16:04:56.120138Z"}], "thread_id": "Thread-1", "execution_time": 0.014841079711914062, "message": null, "adapter_response": {}, "unique_id": "test.snowplow_web.not_null_snowplow_web_page_views_this_run_start_tstamp"}, {"status": "success", "timing": [{"name": "compile", "started_at": "2021-08-19T16:04:56.106010Z", "completed_at": "2021-08-19T16:04:56.120232Z"}, {"name": "execute", "started_at": "2021-08-19T16:04:56.120600Z", "completed_at": "2021-08-19T16:04:56.120604Z"}], "thread_id": "Thread-3", "execution_time": 0.015188932418823242, "message": null, "adapter_response": {}, "unique_id": "test.snowplow_web.unique_snowplow_web_page_views_this_run_event_id"}, {"status": "success", "timing": [{"name": "compile", "started_at": "2021-08-19T16:04:56.121056Z", "completed_at": "2021-08-19T16:04:56.135339Z"}, {"name": "execute", "started_at": "2021-08-19T16:04:56.135488Z", "completed_at": "2021-08-19T16:04:56.135495Z"}], "thread_id": "Thread-4", "execution_time": 0.015002250671386719, "message": null, "adapter_response": {}, "unique_id": "test.snowplow_web.unique_snowplow_web_page_views_this_run_page_view_id"}, {"status": "success", "timing": [{"name": "compile", "started_at": "2021-08-19T16:04:56.125643Z", "completed_at": "2021-08-19T16:04:56.136037Z"}, {"name": "execute", "started_at": "2021-08-19T16:04:56.136210Z", "completed_at": "2021-08-19T16:04:56.136214Z"}], "thread_id": "Thread-1", "execution_time": 0.020392894744873047, "message": null, "adapter_response": {}, "unique_id": "model.snowplow_web.snowplow_web_sessions_lasts"}, {"status": "success", "timing": [{"name": "compile", "started_at": "2021-08-19T16:04:56.130872Z", "completed_at": "2021-08-19T16:04:56.136307Z"}, {"name": "execute", "started_at": "2021-08-19T16:04:56.141573Z", "completed_at": "2021-08-19T16:04:56.141577Z"}], "thread_id": "Thread-3", "execution_time": 0.016287803649902344, "message": null, "adapter_response": {}, "unique_id": "test.snowplow_web.not_null_snowplow_web_sessions_aggs_domain_sessionid"}, {"status": "success", "timing": [{"name": "compile", "started_at": "2021-08-19T16:04:56.136152Z", "completed_at": "2021-08-19T16:04:56.142233Z"}, {"name": "execute", "started_at": "2021-08-19T16:04:56.142563Z", "completed_at": "2021-08-19T16:04:56.142567Z"}], "thread_id": "Thread-4", "execution_time": 0.006895303726196289, "message": null, "adapter_response": {}, "unique_id": "test.snowplow_web.unique_snowplow_web_sessions_aggs_domain_sessionid"}, {"status": "success", "timing": [{"name": "compile", "started_at": "2021-08-19T16:04:56.142667Z", "completed_at": "2021-08-19T16:04:56.175151Z"}, {"name": "execute", "started_at": "2021-08-19T16:04:56.175524Z", "completed_at": "2021-08-19T16:04:56.175529Z"}], "thread_id": "Thread-1", "execution_time": 0.03378605842590332, "message": null, "adapter_response": {}, "unique_id": "model.snowplow_web.snowplow_web_sessions_this_run"}, {"status": "success", "timing": [{"name": "compile", "started_at": "2021-08-19T16:04:56.142711Z", "completed_at": "2021-08-19T16:04:56.175308Z"}, {"name": "execute", "started_at": "2021-08-19T16:04:56.175680Z", "completed_at": "2021-08-19T16:04:56.175684Z"}], "thread_id": "Thread-3", "execution_time": 0.033891916275024414, "message": null, "adapter_response": {}, "unique_id": "test.snowplow_web.not_null_snowplow_web_sessions_lasts_domain_sessionid"}, {"status": "success", "timing": [{"name": "compile", "started_at": "2021-08-19T16:04:56.170598Z", "completed_at": "2021-08-19T16:04:56.175424Z"}, {"name": "execute", "started_at": "2021-08-19T16:04:56.175877Z", "completed_at": "2021-08-19T16:04:56.175881Z"}], "thread_id": "Thread-4", "execution_time": 0.006124258041381836, "message": null, "adapter_response": {}, "unique_id": "test.snowplow_web.unique_snowplow_web_sessions_lasts_domain_sessionid"}, {"status": "success", "timing": [{"name": "compile", "started_at": "2021-08-19T16:04:56.178317Z", "completed_at": "2021-08-19T16:04:56.210693Z"}, {"name": "execute", "started_at": "2021-08-19T16:04:56.210836Z", "completed_at": "2021-08-19T16:04:56.210843Z"}], "thread_id": "Thread-1", "execution_time": 0.03301596641540527, "message": null, "adapter_response": {}, "unique_id": "test.snowplow_web.not_null_snowplow_web_sessions_this_run_absolute_time_in_s"}, {"status": "success", "timing": [{"name": "compile", "started_at": "2021-08-19T16:04:56.178362Z", "completed_at": "2021-08-19T16:04:56.211394Z"}, {"name": "execute", "started_at": "2021-08-19T16:04:56.211556Z", "completed_at": "2021-08-19T16:04:56.211560Z"}], "thread_id": "Thread-4", "execution_time": 0.03806304931640625, "message": null, "adapter_response": {}, "unique_id": "test.snowplow_web.not_null_snowplow_web_sessions_this_run_domain_sessionid"}, {"status": "success", "timing": [{"name": "compile", "started_at": "2021-08-19T16:04:56.211495Z", "completed_at": "2021-08-19T16:04:56.220877Z"}, {"name": "execute", "started_at": "2021-08-19T16:04:56.221028Z", "completed_at": "2021-08-19T16:04:56.221034Z"}], "thread_id": "Thread-1", "execution_time": 0.010286808013916016, "message": null, "adapter_response": {}, "unique_id": "test.snowplow_web.not_null_snowplow_web_sessions_this_run_domain_sessionidx"}, {"status": "success", "timing": [{"name": "compile", "started_at": "2021-08-19T16:04:56.216590Z", "completed_at": "2021-08-19T16:04:56.221900Z"}, {"name": "execute", "started_at": "2021-08-19T16:04:56.222123Z", "completed_at": "2021-08-19T16:04:56.222128Z"}], "thread_id": "Thread-4", "execution_time": 0.010588884353637695, "message": null, "adapter_response": {}, "unique_id": "test.snowplow_web.not_null_snowplow_web_sessions_this_run_domain_userid"}, {"status": "success", "timing": [{"name": "compile", "started_at": "2021-08-19T16:04:56.222055Z", "completed_at": "2021-08-19T16:04:56.228254Z"}, {"name": "execute", "started_at": "2021-08-19T16:04:56.228469Z", "completed_at": "2021-08-19T16:04:56.228473Z"}], "thread_id": "Thread-1", "execution_time": 0.012412071228027344, "message": null, "adapter_response": {}, "unique_id": "test.snowplow_web.not_null_snowplow_web_sessions_this_run_end_tstamp"}, {"status": "success", "timing": [{"name": "compile", "started_at": "2021-08-19T16:04:56.228374Z", "completed_at": "2021-08-19T16:04:56.235327Z"}, {"name": "execute", "started_at": "2021-08-19T16:04:56.239824Z", "completed_at": "2021-08-19T16:04:56.239829Z"}], "thread_id": "Thread-4", "execution_time": 0.012174129486083984, "message": null, "adapter_response": {}, "unique_id": "test.snowplow_web.not_null_snowplow_web_sessions_this_run_engaged_time_in_s"}, {"status": "success", "timing": [{"name": "compile", "started_at": "2021-08-19T16:04:56.235287Z", "completed_at": "2021-08-19T16:04:56.240707Z"}, {"name": "execute", "started_at": "2021-08-19T16:04:56.240881Z", "completed_at": "2021-08-19T16:04:56.240885Z"}], "thread_id": "Thread-1", "execution_time": 0.01044321060180664, "message": null, "adapter_response": {}, "unique_id": "test.snowplow_web.not_null_snowplow_web_sessions_this_run_first_page_url"}, {"status": "success", "timing": [{"name": "compile", "started_at": "2021-08-19T16:04:56.240818Z", "completed_at": "2021-08-19T16:04:56.250279Z"}, {"name": "execute", "started_at": "2021-08-19T16:04:56.250410Z", "completed_at": "2021-08-19T16:04:56.250415Z"}], "thread_id": "Thread-4", "execution_time": 0.010015010833740234, "message": null, "adapter_response": {}, "unique_id": "test.snowplow_web.not_null_snowplow_web_sessions_this_run_last_page_url"}, {"status": "success", "timing": [{"name": "compile", "started_at": "2021-08-19T16:04:56.245931Z", "completed_at": "2021-08-19T16:04:56.250749Z"}, {"name": "execute", "started_at": "2021-08-19T16:04:56.251022Z", "completed_at": "2021-08-19T16:04:56.251026Z"}], "thread_id": "Thread-1", "execution_time": 0.005448102951049805, "message": null, "adapter_response": {}, "unique_id": "test.snowplow_web.not_null_snowplow_web_sessions_this_run_network_userid"}, {"status": "success", "timing": [{"name": "compile", "started_at": "2021-08-19T16:04:56.251134Z", "completed_at": "2021-08-19T16:04:56.260308Z"}, {"name": "execute", "started_at": "2021-08-19T16:04:56.260425Z", "completed_at": "2021-08-19T16:04:56.260429Z"}], "thread_id": "Thread-4", "execution_time": 0.009696006774902344, "message": null, "adapter_response": {}, "unique_id": "test.snowplow_web.not_null_snowplow_web_sessions_this_run_page_views"}, {"status": "success", "timing": [{"name": "compile", "started_at": "2021-08-19T16:04:56.255971Z", "completed_at": "2021-08-19T16:04:56.260862Z"}, {"name": "execute", "started_at": "2021-08-19T16:04:56.261059Z", "completed_at": "2021-08-19T16:04:56.261063Z"}], "thread_id": "Thread-1", "execution_time": 0.009706974029541016, "message": null, "adapter_response": {}, "unique_id": "test.snowplow_web.not_null_snowplow_web_sessions_this_run_start_tstamp"}, {"status": "success", "timing": [{"name": "compile", "started_at": "2021-08-19T16:04:56.261009Z", "completed_at": "2021-08-19T16:04:56.265779Z"}, {"name": "execute", "started_at": "2021-08-19T16:04:56.265902Z", "completed_at": "2021-08-19T16:04:56.265906Z"}], "thread_id": "Thread-4", "execution_time": 0.005324125289916992, "message": null, "adapter_response": {}, "unique_id": "test.snowplow_web.unique_snowplow_web_sessions_this_run_domain_sessionid"}, {"status": "success", "timing": [{"name": "compile", "started_at": "2021-08-19T16:04:56.002236Z", "completed_at": "2021-08-19T16:04:57.267838Z"}, {"name": "execute", "started_at": "2021-08-19T16:04:57.268310Z", "completed_at": "2021-08-19T16:04:57.268340Z"}], "thread_id": "Thread-2", "execution_time": 1.2674610614776611, "message": null, "adapter_response": {}, "unique_id": "model.snowplow_web.snowplow_web_page_views"}, {"status": "success", "timing": [{"name": "compile", "started_at": "2021-08-19T16:04:57.273346Z", "completed_at": "2021-08-19T16:04:57.308894Z"}, {"name": "execute", "started_at": "2021-08-19T16:04:57.309376Z", "completed_at": "2021-08-19T16:04:57.309387Z"}], "thread_id": "Thread-4", "execution_time": 0.03772306442260742, "message": null, "adapter_response": {}, "unique_id": "test.snowplow_web.not_null_snowplow_web_page_views_absolute_time_in_s"}, {"status": "success", "timing": [{"name": "compile", "started_at": "2021-08-19T16:04:57.273210Z", "completed_at": "2021-08-19T16:04:57.309132Z"}, {"name": "execute", "started_at": "2021-08-19T16:04:57.309774Z", "completed_at": "2021-08-19T16:04:57.309781Z"}], "thread_id": "Thread-1", "execution_time": 0.03876495361328125, "message": null, "adapter_response": {}, "unique_id": "model.snowplow_web_integration_tests.snowplow_web_page_views_actual"}, {"status": "success", "timing": [{"name": "compile", "started_at": "2021-08-19T16:04:57.273465Z", "completed_at": "2021-08-19T16:04:57.309542Z"}, {"name": "execute", "started_at": "2021-08-19T16:04:57.310256Z", "completed_at": "2021-08-19T16:04:57.310262Z"}], "thread_id": "Thread-2", "execution_time": 0.0382382869720459, "message": null, "adapter_response": {}, "unique_id": "test.snowplow_web.not_null_snowplow_web_page_views_collector_tstamp"}, {"status": "success", "timing": [{"name": "compile", "started_at": "2021-08-19T16:04:57.312082Z", "completed_at": "2021-08-19T16:04:57.334384Z"}, {"name": "execute", "started_at": "2021-08-19T16:04:57.334645Z", "completed_at": "2021-08-19T16:04:57.334653Z"}], "thread_id": "Thread-4", "execution_time": 0.02348804473876953, "message": null, "adapter_response": {}, "unique_id": "test.snowplow_web.not_null_snowplow_web_page_views_derived_tstamp"}, {"status": "success", "timing": [{"name": "compile", "started_at": "2021-08-19T16:04:57.312353Z", "completed_at": "2021-08-19T16:04:57.335026Z"}, {"name": "execute", "started_at": "2021-08-19T16:04:57.335590Z", "completed_at": "2021-08-19T16:04:57.335595Z"}], "thread_id": "Thread-1", "execution_time": 0.0247647762298584, "message": null, "adapter_response": {}, "unique_id": "test.snowplow_web.not_null_snowplow_web_page_views_domain_sessionid"}, {"status": "success", "timing": [{"name": "compile", "started_at": "2021-08-19T16:04:57.320410Z", "completed_at": "2021-08-19T16:04:57.335443Z"}, {"name": "execute", "started_at": "2021-08-19T16:04:57.336286Z", "completed_at": "2021-08-19T16:04:57.336291Z"}], "thread_id": "Thread-2", "execution_time": 0.02476215362548828, "message": null, "adapter_response": {}, "unique_id": "test.snowplow_web.not_null_snowplow_web_page_views_domain_sessionidx"}, {"status": "success", "timing": [{"name": "compile", "started_at": "2021-08-19T16:04:57.336774Z", "completed_at": "2021-08-19T16:04:57.349417Z"}, {"name": "execute", "started_at": "2021-08-19T16:04:57.354519Z", "completed_at": "2021-08-19T16:04:57.354525Z"}], "thread_id": "Thread-4", "execution_time": 0.01888108253479004, "message": null, "adapter_response": {}, "unique_id": "test.snowplow_web.not_null_snowplow_web_page_views_domain_userid"}, {"status": "success", "timing": [{"name": "compile", "started_at": "2021-08-19T16:04:57.343299Z", "completed_at": "2021-08-19T16:04:57.354947Z"}, {"name": "execute", "started_at": "2021-08-19T16:04:57.355255Z", "completed_at": "2021-08-19T16:04:57.355260Z"}], "thread_id": "Thread-1", "execution_time": 0.012710094451904297, "message": null, "adapter_response": {}, "unique_id": "test.snowplow_web.not_null_snowplow_web_page_views_dvce_created_tstamp"}, {"status": "success", "timing": [{"name": "compile", "started_at": "2021-08-19T16:04:57.343377Z", "completed_at": "2021-08-19T16:04:57.355365Z"}, {"name": "execute", "started_at": "2021-08-19T16:04:57.355737Z", "completed_at": "2021-08-19T16:04:57.355741Z"}], "thread_id": "Thread-2", "execution_time": 0.0129547119140625, "message": null, "adapter_response": {}, "unique_id": "test.snowplow_web.not_null_snowplow_web_page_views_end_tstamp"}, {"status": "success", "timing": [{"name": "compile", "started_at": "2021-08-19T16:04:57.355850Z", "completed_at": "2021-08-19T16:04:57.366011Z"}, {"name": "execute", "started_at": "2021-08-19T16:04:57.370673Z", "completed_at": "2021-08-19T16:04:57.370679Z"}], "thread_id": "Thread-4", "execution_time": 0.015471220016479492, "message": null, "adapter_response": {}, "unique_id": "test.snowplow_web.not_null_snowplow_web_page_views_engaged_time_in_s"}, {"status": "success", "timing": [{"name": "compile", "started_at": "2021-08-19T16:04:57.361136Z", "completed_at": "2021-08-19T16:04:57.371014Z"}, {"name": "execute", "started_at": "2021-08-19T16:04:57.371218Z", "completed_at": "2021-08-19T16:04:57.371222Z"}], "thread_id": "Thread-1", "execution_time": 0.010786771774291992, "message": null, "adapter_response": {}, "unique_id": "test.snowplow_web.not_null_snowplow_web_page_views_event_id"}, {"status": "success", "timing": [{"name": "compile", "started_at": "2021-08-19T16:04:57.365913Z", "completed_at": "2021-08-19T16:04:57.371373Z"}, {"name": "execute", "started_at": "2021-08-19T16:04:57.371723Z", "completed_at": "2021-08-19T16:04:57.371727Z"}], "thread_id": "Thread-2", "execution_time": 0.010855913162231445, "message": null, "adapter_response": {}, "unique_id": "test.snowplow_web.not_null_snowplow_web_page_views_network_userid"}, {"status": "success", "timing": [{"name": "compile", "started_at": "2021-08-19T16:04:57.371832Z", "completed_at": "2021-08-19T16:04:57.381397Z"}, {"name": "execute", "started_at": "2021-08-19T16:04:57.381590Z", "completed_at": "2021-08-19T16:04:57.381595Z"}], "thread_id": "Thread-4", "execution_time": 0.015382051467895508, "message": null, "adapter_response": {}, "unique_id": "test.snowplow_web.not_null_snowplow_web_page_views_page_url"}, {"status": "success", "timing": [{"name": "compile", "started_at": "2021-08-19T16:04:57.376801Z", "completed_at": "2021-08-19T16:04:57.386926Z"}, {"name": "execute", "started_at": "2021-08-19T16:04:57.387211Z", "completed_at": "2021-08-19T16:04:57.387216Z"}], "thread_id": "Thread-1", "execution_time": 0.011095046997070312, "message": null, "adapter_response": {}, "unique_id": "test.snowplow_web.not_null_snowplow_web_page_views_page_view_id"}, {"status": "success", "timing": [{"name": "compile", "started_at": "2021-08-19T16:04:57.381504Z", "completed_at": "2021-08-19T16:04:57.387461Z"}, {"name": "execute", "started_at": "2021-08-19T16:04:57.387746Z", "completed_at": "2021-08-19T16:04:57.387750Z"}], "thread_id": "Thread-2", "execution_time": 0.015446662902832031, "message": null, "adapter_response": {}, "unique_id": "test.snowplow_web.not_null_snowplow_web_page_views_page_view_in_session_index"}, {"status": "success", "timing": [{"name": "compile", "started_at": "2021-08-19T16:04:57.387692Z", "completed_at": "2021-08-19T16:04:57.392863Z"}, {"name": "execute", "started_at": "2021-08-19T16:04:57.397276Z", "completed_at": "2021-08-19T16:04:57.397281Z"}], "thread_id": "Thread-4", "execution_time": 0.01854109764099121, "message": null, "adapter_response": {}, "unique_id": "test.snowplow_web.not_null_snowplow_web_page_views_page_views_in_session"}, {"status": "success", "timing": [{"name": "compile", "started_at": "2021-08-19T16:04:57.392689Z", "completed_at": "2021-08-19T16:04:57.405951Z"}, {"name": "execute", "started_at": "2021-08-19T16:04:57.406226Z", "completed_at": "2021-08-19T16:04:57.406230Z"}], "thread_id": "Thread-1", "execution_time": 0.014177083969116211, "message": null, "adapter_response": {}, "unique_id": "test.snowplow_web.not_null_snowplow_web_page_views_start_tstamp"}, {"status": "success", "timing": [{"name": "compile", "started_at": "2021-08-19T16:04:57.397220Z", "completed_at": "2021-08-19T16:04:57.406632Z"}, {"name": "execute", "started_at": "2021-08-19T16:04:57.406888Z", "completed_at": "2021-08-19T16:04:57.406892Z"}], "thread_id": "Thread-2", "execution_time": 0.018803834915161133, "message": null, "adapter_response": {}, "unique_id": "test.snowplow_web.snowplow_tests_page_view_in_session_values"}, {"status": "success", "timing": [{"name": "compile", "started_at": "2021-08-19T16:04:57.406731Z", "completed_at": "2021-08-19T16:04:57.416259Z"}, {"name": "execute", "started_at": "2021-08-19T16:04:57.416486Z", "completed_at": "2021-08-19T16:04:57.416490Z"}], "thread_id": "Thread-4", "execution_time": 0.020147323608398438, "message": null, "adapter_response": {}, "unique_id": "test.snowplow_web.unique_snowplow_web_page_views_event_id"}, {"status": "success", "timing": [{"name": "compile", "started_at": "2021-08-19T16:04:57.411656Z", "completed_at": "2021-08-19T16:04:57.422665Z"}, {"name": "execute", "started_at": "2021-08-19T16:04:57.426591Z", "completed_at": "2021-08-19T16:04:57.426595Z"}], "thread_id": "Thread-1", "execution_time": 0.01555013656616211, "message": null, "adapter_response": {}, "unique_id": "test.snowplow_web.unique_snowplow_web_page_views_page_view_id"}, {"status": "success", "timing": [{"name": "compile", "started_at": "2021-08-19T16:04:56.178273Z", "completed_at": "2021-08-19T16:04:57.540752Z"}, {"name": "execute", "started_at": "2021-08-19T16:04:57.540974Z", "completed_at": "2021-08-19T16:04:57.540983Z"}], "thread_id": "Thread-3", "execution_time": 1.363403081893921, "message": null, "adapter_response": {}, "unique_id": "model.snowplow_web.snowplow_web_sessions"}, {"status": "success", "timing": [{"name": "compile", "started_at": "2021-08-19T16:04:57.542740Z", "completed_at": "2021-08-19T16:04:57.584458Z"}, {"name": "execute", "started_at": "2021-08-19T16:04:57.584620Z", "completed_at": "2021-08-19T16:04:57.584629Z"}], "thread_id": "Thread-1", "execution_time": 0.042569875717163086, "message": null, "adapter_response": {}, "unique_id": "model.snowplow_web_integration_tests.snowplow_web_sessions_actual"}, {"status": "success", "timing": [{"name": "compile", "started_at": "2021-08-19T16:04:57.573141Z", "completed_at": "2021-08-19T16:04:57.584958Z"}, {"name": "execute", "started_at": "2021-08-19T16:04:57.585626Z", "completed_at": "2021-08-19T16:04:57.585630Z"}], "thread_id": "Thread-3", "execution_time": 0.04348397254943848, "message": null, "adapter_response": {}, "unique_id": "test.snowplow_web.not_null_snowplow_web_sessions_absolute_time_in_s"}, {"status": "success", "timing": [{"name": "compile", "started_at": "2021-08-19T16:04:57.586151Z", "completed_at": "2021-08-19T16:04:57.595951Z"}, {"name": "execute", "started_at": "2021-08-19T16:04:57.596091Z", "completed_at": "2021-08-19T16:04:57.596097Z"}], "thread_id": "Thread-1", "execution_time": 0.010458230972290039, "message": null, "adapter_response": {}, "unique_id": "test.snowplow_web.not_null_snowplow_web_sessions_domain_sessionid"}, {"status": "success", "timing": [{"name": "compile", "started_at": "2021-08-19T16:04:57.591192Z", "completed_at": "2021-08-19T16:04:57.601187Z"}, {"name": "execute", "started_at": "2021-08-19T16:04:57.601324Z", "completed_at": "2021-08-19T16:04:57.601329Z"}], "thread_id": "Thread-3", "execution_time": 0.010524272918701172, "message": null, "adapter_response": {}, "unique_id": "test.snowplow_web.not_null_snowplow_web_sessions_domain_sessionidx"}, {"status": "success", "timing": [{"name": "compile", "started_at": "2021-08-19T16:04:57.596534Z", "completed_at": "2021-08-19T16:04:57.601671Z"}, {"name": "execute", "started_at": "2021-08-19T16:04:57.601963Z", "completed_at": "2021-08-19T16:04:57.601967Z"}], "thread_id": "Thread-1", "execution_time": 0.0057790279388427734, "message": null, "adapter_response": {}, "unique_id": "test.snowplow_web.not_null_snowplow_web_sessions_domain_userid"}, {"status": "success", "timing": [{"name": "compile", "started_at": "2021-08-19T16:04:57.602080Z", "completed_at": "2021-08-19T16:04:57.611533Z"}, {"name": "execute", "started_at": "2021-08-19T16:04:57.611688Z", "completed_at": "2021-08-19T16:04:57.611694Z"}], "thread_id": "Thread-3", "execution_time": 0.010072946548461914, "message": null, "adapter_response": {}, "unique_id": "test.snowplow_web.not_null_snowplow_web_sessions_end_tstamp"}, {"status": "success", "timing": [{"name": "compile", "started_at": "2021-08-19T16:04:57.606981Z", "completed_at": "2021-08-19T16:04:57.612107Z"}, {"name": "execute", "started_at": "2021-08-19T16:04:57.612390Z", "completed_at": "2021-08-19T16:04:57.612395Z"}], "thread_id": "Thread-1", "execution_time": 0.005885124206542969, "message": null, "adapter_response": {}, "unique_id": "test.snowplow_web.not_null_snowplow_web_sessions_engaged_time_in_s"}, {"status": "success", "timing": [{"name": "compile", "started_at": "2021-08-19T16:04:57.612538Z", "completed_at": "2021-08-19T16:04:57.623902Z"}, {"name": "execute", "started_at": "2021-08-19T16:04:57.624088Z", "completed_at": "2021-08-19T16:04:57.624095Z"}], "thread_id": "Thread-3", "execution_time": 0.012167930603027344, "message": null, "adapter_response": {}, "unique_id": "test.snowplow_web.not_null_snowplow_web_sessions_first_page_url"}, {"status": "success", "timing": [{"name": "compile", "started_at": "2021-08-19T16:04:57.619234Z", "completed_at": "2021-08-19T16:04:57.624194Z"}, {"name": "execute", "started_at": "2021-08-19T16:04:57.624511Z", "completed_at": "2021-08-19T16:04:57.624516Z"}], "thread_id": "Thread-1", "execution_time": 0.005776882171630859, "message": null, "adapter_response": {}, "unique_id": "test.snowplow_web.not_null_snowplow_web_sessions_last_page_url"}, {"status": "success", "timing": [{"name": "compile", "started_at": "2021-08-19T16:04:57.625155Z", "completed_at": "2021-08-19T16:04:57.634413Z"}, {"name": "execute", "started_at": "2021-08-19T16:04:57.642527Z", "completed_at": "2021-08-19T16:04:57.642535Z"}], "thread_id": "Thread-3", "execution_time": 0.017861127853393555, "message": null, "adapter_response": {}, "unique_id": "test.snowplow_web.not_null_snowplow_web_sessions_network_userid"}, {"status": "success", "timing": [{"name": "compile", "started_at": "2021-08-19T16:04:57.629832Z", "completed_at": "2021-08-19T16:04:57.642948Z"}, {"name": "execute", "started_at": "2021-08-19T16:04:57.643307Z", "completed_at": "2021-08-19T16:04:57.643311Z"}], "thread_id": "Thread-1", "execution_time": 0.018354177474975586, "message": null, "adapter_response": {}, "unique_id": "test.snowplow_web.not_null_snowplow_web_sessions_page_views"}, {"status": "success", "timing": [{"name": "compile", "started_at": "2021-08-19T16:04:57.643450Z", "completed_at": "2021-08-19T16:04:57.652913Z"}, {"name": "execute", "started_at": "2021-08-19T16:04:57.653049Z", "completed_at": "2021-08-19T16:04:57.653055Z"}], "thread_id": "Thread-3", "execution_time": 0.010252952575683594, "message": null, "adapter_response": {}, "unique_id": "test.snowplow_web.not_null_snowplow_web_sessions_start_tstamp"}, {"status": "success", "timing": [{"name": "compile", "started_at": "2021-08-19T16:04:57.648414Z", "completed_at": "2021-08-19T16:04:57.653145Z"}, {"name": "execute", "started_at": "2021-08-19T16:04:57.653487Z", "completed_at": "2021-08-19T16:04:57.653491Z"}], "thread_id": "Thread-1", "execution_time": 0.0055048465728759766, "message": null, "adapter_response": {}, "unique_id": "test.snowplow_web.unique_snowplow_web_sessions_domain_sessionid"}, {"status": "success", "timing": [{"name": "compile", "started_at": "2021-08-19T16:04:57.416416Z", "completed_at": "2021-08-19T16:04:57.771745Z"}, {"name": "execute", "started_at": "2021-08-19T16:04:57.771971Z", "completed_at": "2021-08-19T16:04:57.771981Z"}], "thread_id": "Thread-2", "execution_time": 0.35611486434936523, "message": null, "adapter_response": {}, "unique_id": "test.snowplow_web_integration_tests.dbt_utils_equality_snowplow_web_page_views_actual_ref_snowplow_web_page_views_expected_stg_"}, {"status": "success", "timing": [{"name": "compile", "started_at": "2021-08-19T16:04:57.654068Z", "completed_at": "2021-08-19T16:04:57.970556Z"}, {"name": "execute", "started_at": "2021-08-19T16:04:57.971059Z", "completed_at": "2021-08-19T16:04:57.971073Z"}], "thread_id": "Thread-3", "execution_time": 0.31772613525390625, "message": null, "adapter_response": {}, "unique_id": "test.snowplow_web_integration_tests.dbt_utils_equality_snowplow_web_sessions_actual_ref_snowplow_web_sessions_expected_stg_"}, {"status": "success", "timing": [{"name": "compile", "started_at": "2021-08-19T16:04:57.542502Z", "completed_at": "2021-08-19T16:04:58.878809Z"}, {"name": "execute", "started_at": "2021-08-19T16:04:58.879217Z", "completed_at": "2021-08-19T16:04:58.879238Z"}], "thread_id": "Thread-4", "execution_time": 1.3377621173858643, "message": null, "adapter_response": {}, "unique_id": "model.snowplow_web.snowplow_web_users_sessions_this_run"}, {"status": "success", "timing": [{"name": "compile", "started_at": "2021-08-19T16:04:58.882662Z", "completed_at": "2021-08-19T16:04:58.914134Z"}, {"name": "execute", "started_at": "2021-08-19T16:04:58.914554Z", "completed_at": "2021-08-19T16:04:58.914566Z"}], "thread_id": "Thread-2", "execution_time": 0.033550262451171875, "message": null, "adapter_response": {}, "unique_id": "test.snowplow_web.not_null_snowplow_web_users_sessions_this_run_domain_sessionid"}, {"status": "success", "timing": [{"name": "compile", "started_at": "2021-08-19T16:04:58.882782Z", "completed_at": "2021-08-19T16:04:58.914365Z"}, {"name": "execute", "started_at": "2021-08-19T16:04:58.914815Z", "completed_at": "2021-08-19T16:04:58.914823Z"}], "thread_id": "Thread-3", "execution_time": 0.0333712100982666, "message": null, "adapter_response": {}, "unique_id": "test.snowplow_web.unique_snowplow_web_users_sessions_this_run_domain_sessionid"}, {"status": "success", "timing": [{"name": "compile", "started_at": "2021-08-19T16:04:58.882528Z", "completed_at": "2021-08-19T16:04:58.914997Z"}, {"name": "execute", "started_at": "2021-08-19T16:04:58.915700Z", "completed_at": "2021-08-19T16:04:58.915708Z"}], "thread_id": "Thread-1", "execution_time": 0.03481030464172363, "message": null, "adapter_response": {}, "unique_id": "model.snowplow_web.snowplow_web_users_aggs"}, {"status": "success", "timing": [{"name": "compile", "started_at": "2021-08-19T16:04:58.917447Z", "completed_at": "2021-08-19T16:04:58.939186Z"}, {"name": "execute", "started_at": "2021-08-19T16:04:58.939531Z", "completed_at": "2021-08-19T16:04:58.939539Z"}], "thread_id": "Thread-4", "execution_time": 0.023168087005615234, "message": null, "adapter_response": {}, "unique_id": "model.snowplow_web.snowplow_web_users_lasts"}, {"status": "success", "timing": [{"name": "compile", "started_at": "2021-08-19T16:04:58.917518Z", "completed_at": "2021-08-19T16:04:58.939351Z"}, {"name": "execute", "started_at": "2021-08-19T16:04:58.939699Z", "completed_at": "2021-08-19T16:04:58.939705Z"}], "thread_id": "Thread-2", "execution_time": 0.02313399314880371, "message": null, "adapter_response": {}, "unique_id": "test.snowplow_web.not_null_snowplow_web_users_aggs_domain_userid"}, {"status": "success", "timing": [{"name": "compile", "started_at": "2021-08-19T16:04:58.917582Z", "completed_at": "2021-08-19T16:04:58.939830Z"}, {"name": "execute", "started_at": "2021-08-19T16:04:58.940299Z", "completed_at": "2021-08-19T16:04:58.940304Z"}], "thread_id": "Thread-3", "execution_time": 0.023593902587890625, "message": null, "adapter_response": {}, "unique_id": "test.snowplow_web.unique_snowplow_web_users_aggs_domain_userid"}, {"status": "success", "timing": [{"name": "compile", "started_at": "2021-08-19T16:04:58.941552Z", "completed_at": "2021-08-19T16:04:58.966652Z"}, {"name": "execute", "started_at": "2021-08-19T16:04:58.966879Z", "completed_at": "2021-08-19T16:04:58.966885Z"}], "thread_id": "Thread-4", "execution_time": 0.02602410316467285, "message": null, "adapter_response": {}, "unique_id": "test.snowplow_web.not_null_snowplow_web_users_lasts_domain_userid"}, {"status": "success", "timing": [{"name": "compile", "started_at": "2021-08-19T16:04:58.941596Z", "completed_at": "2021-08-19T16:04:58.966771Z"}, {"name": "execute", "started_at": "2021-08-19T16:04:58.967018Z", "completed_at": "2021-08-19T16:04:58.967021Z"}], "thread_id": "Thread-2", "execution_time": 0.026031970977783203, "message": null, "adapter_response": {}, "unique_id": "test.snowplow_web.unique_snowplow_web_users_lasts_domain_userid"}, {"status": "success", "timing": [{"name": "compile", "started_at": "2021-08-19T16:04:58.941503Z", "completed_at": "2021-08-19T16:04:58.967104Z"}, {"name": "execute", "started_at": "2021-08-19T16:04:58.967481Z", "completed_at": "2021-08-19T16:04:58.967484Z"}], "thread_id": "Thread-1", "execution_time": 0.02672100067138672, "message": null, "adapter_response": {}, "unique_id": "model.snowplow_web.snowplow_web_users_this_run"}, {"status": "success", "timing": [{"name": "compile", "started_at": "2021-08-19T16:04:58.968774Z", "completed_at": "2021-08-19T16:04:58.996422Z"}, {"name": "execute", "started_at": "2021-08-19T16:04:58.996561Z", "completed_at": "2021-08-19T16:04:58.996567Z"}], "thread_id": "Thread-4", "execution_time": 0.028287887573242188, "message": null, "adapter_response": {}, "unique_id": "test.snowplow_web.not_null_snowplow_web_users_this_run_domain_userid"}, {"status": "success", "timing": [{"name": "compile", "started_at": "2021-08-19T16:04:58.980795Z", "completed_at": "2021-08-19T16:04:59.001552Z"}, {"name": "execute", "started_at": "2021-08-19T16:04:59.001684Z", "completed_at": "2021-08-19T16:04:59.001689Z"}], "thread_id": "Thread-2", "execution_time": 0.03324532508850098, "message": null, "adapter_response": {}, "unique_id": "test.snowplow_web.not_null_snowplow_web_users_this_run_end_tstamp"}, {"status": "success", "timing": [{"name": "compile", "started_at": "2021-08-19T16:04:58.987679Z", "completed_at": "2021-08-19T16:04:59.001981Z"}, {"name": "execute", "started_at": "2021-08-19T16:04:59.002297Z", "completed_at": "2021-08-19T16:04:59.002301Z"}], "thread_id": "Thread-1", "execution_time": 0.03396296501159668, "message": null, "adapter_response": {}, "unique_id": "test.snowplow_web.not_null_snowplow_web_users_this_run_engaged_time_in_s"}, {"status": "success", "timing": [{"name": "compile", "started_at": "2021-08-19T16:04:58.997012Z", "completed_at": "2021-08-19T16:04:59.002187Z"}, {"name": "execute", "started_at": "2021-08-19T16:04:59.002546Z", "completed_at": "2021-08-19T16:04:59.002551Z"}], "thread_id": "Thread-4", "execution_time": 0.006081104278564453, "message": null, "adapter_response": {}, "unique_id": "test.snowplow_web.not_null_snowplow_web_users_this_run_first_page_url"}, {"status": "success", "timing": [{"name": "compile", "started_at": "2021-08-19T16:04:59.002856Z", "completed_at": "2021-08-19T16:04:59.008258Z"}, {"name": "execute", "started_at": "2021-08-19T16:04:59.008534Z", "completed_at": "2021-08-19T16:04:59.008539Z"}], "thread_id": "Thread-2", "execution_time": 0.0158693790435791, "message": null, "adapter_response": {}, "unique_id": "test.snowplow_web.not_null_snowplow_web_users_this_run_last_page_url"}, {"status": "success", "timing": [{"name": "compile", "started_at": "2021-08-19T16:04:59.008369Z", "completed_at": "2021-08-19T16:04:59.023540Z"}, {"name": "execute", "started_at": "2021-08-19T16:04:59.023928Z", "completed_at": "2021-08-19T16:04:59.023934Z"}], "thread_id": "Thread-1", "execution_time": 0.016985177993774414, "message": null, "adapter_response": {}, "unique_id": "test.snowplow_web.not_null_snowplow_web_users_this_run_network_userid"}, {"status": "success", "timing": [{"name": "compile", "started_at": "2021-08-19T16:04:59.008455Z", "completed_at": "2021-08-19T16:04:59.023814Z"}, {"name": "execute", "started_at": "2021-08-19T16:04:59.024207Z", "completed_at": "2021-08-19T16:04:59.024211Z"}], "thread_id": "Thread-4", "execution_time": 0.016949892044067383, "message": null, "adapter_response": {}, "unique_id": "test.snowplow_web.not_null_snowplow_web_users_this_run_page_views"}, {"status": "success", "timing": [{"name": "compile", "started_at": "2021-08-19T16:04:59.019061Z", "completed_at": "2021-08-19T16:04:59.024410Z"}, {"name": "execute", "started_at": "2021-08-19T16:04:59.024822Z", "completed_at": "2021-08-19T16:04:59.024826Z"}], "thread_id": "Thread-2", "execution_time": 0.006345033645629883, "message": null, "adapter_response": {}, "unique_id": "test.snowplow_web.not_null_snowplow_web_users_this_run_sessions"}, {"status": "success", "timing": [{"name": "compile", "started_at": "2021-08-19T16:04:59.025574Z", "completed_at": "2021-08-19T16:04:59.034543Z"}, {"name": "execute", "started_at": "2021-08-19T16:04:59.034774Z", "completed_at": "2021-08-19T16:04:59.034779Z"}], "thread_id": "Thread-1", "execution_time": 0.009749889373779297, "message": null, "adapter_response": {}, "unique_id": "test.snowplow_web.not_null_snowplow_web_users_this_run_start_tstamp"}, {"status": "success", "timing": [{"name": "compile", "started_at": "2021-08-19T16:04:59.025620Z", "completed_at": "2021-08-19T16:04:59.034651Z"}, {"name": "execute", "started_at": "2021-08-19T16:04:59.034881Z", "completed_at": "2021-08-19T16:04:59.034885Z"}], "thread_id": "Thread-4", "execution_time": 0.009764909744262695, "message": null, "adapter_response": {}, "unique_id": "test.snowplow_web.unique_snowplow_web_users_this_run_domain_userid"}, {"status": "success", "timing": [{"name": "compile", "started_at": "2021-08-19T16:04:58.968618Z", "completed_at": "2021-08-19T16:05:00.320832Z"}, {"name": "execute", "started_at": "2021-08-19T16:05:00.321607Z", "completed_at": "2021-08-19T16:05:00.321640Z"}], "thread_id": "Thread-3", "execution_time": 1.3543410301208496, "message": null, "adapter_response": {}, "unique_id": "model.snowplow_web.snowplow_web_users"}, {"status": "success", "timing": [{"name": "compile", "started_at": "2021-08-19T16:05:00.326291Z", "completed_at": "2021-08-19T16:05:00.368640Z"}, {"name": "execute", "started_at": "2021-08-19T16:05:00.369233Z", "completed_at": "2021-08-19T16:05:00.369246Z"}], "thread_id": "Thread-2", "execution_time": 0.045121192932128906, "message": null, "adapter_response": {}, "unique_id": "model.snowplow_web_integration_tests.snowplow_web_users_actual"}, {"status": "success", "timing": [{"name": "compile", "started_at": "2021-08-19T16:05:00.326739Z", "completed_at": "2021-08-19T16:05:00.369022Z"}, {"name": "execute", "started_at": "2021-08-19T16:05:00.369615Z", "completed_at": "2021-08-19T16:05:00.369622Z"}], "thread_id": "Thread-1", "execution_time": 0.04490494728088379, "message": null, "adapter_response": {}, "unique_id": "test.snowplow_web.not_null_snowplow_web_users_domain_userid"}, {"status": "success", "timing": [{"name": "compile", "started_at": "2021-08-19T16:05:00.326870Z", "completed_at": "2021-08-19T16:05:00.369418Z"}, {"name": "execute", "started_at": "2021-08-19T16:05:00.370156Z", "completed_at": "2021-08-19T16:05:00.370161Z"}], "thread_id": "Thread-4", "execution_time": 0.04510164260864258, "message": null, "adapter_response": {}, "unique_id": "test.snowplow_web.not_null_snowplow_web_users_end_tstamp"}, {"status": "success", "timing": [{"name": "compile", "started_at": "2021-08-19T16:05:00.340161Z", "completed_at": "2021-08-19T16:05:00.369751Z"}, {"name": "execute", "started_at": "2021-08-19T16:05:00.370538Z", "completed_at": "2021-08-19T16:05:00.370543Z"}], "thread_id": "Thread-3", "execution_time": 0.044981956481933594, "message": null, "adapter_response": {}, "unique_id": "test.snowplow_web.not_null_snowplow_web_users_engaged_time_in_s"}, {"status": "success", "timing": [{"name": "compile", "started_at": "2021-08-19T16:05:00.372157Z", "completed_at": "2021-08-19T16:05:00.396410Z"}, {"name": "execute", "started_at": "2021-08-19T16:05:00.396776Z", "completed_at": "2021-08-19T16:05:00.396782Z"}], "thread_id": "Thread-2", "execution_time": 0.02573680877685547, "message": null, "adapter_response": {}, "unique_id": "test.snowplow_web.not_null_snowplow_web_users_first_page_url"}, {"status": "success", "timing": [{"name": "compile", "started_at": "2021-08-19T16:05:00.372412Z", "completed_at": "2021-08-19T16:05:00.396652Z"}, {"name": "execute", "started_at": "2021-08-19T16:05:00.396941Z", "completed_at": "2021-08-19T16:05:00.396946Z"}], "thread_id": "Thread-1", "execution_time": 0.0257110595703125, "message": null, "adapter_response": {}, "unique_id": "test.snowplow_web.not_null_snowplow_web_users_last_page_url"}, {"status": "success", "timing": [{"name": "compile", "started_at": "2021-08-19T16:05:00.379219Z", "completed_at": "2021-08-19T16:05:00.397047Z"}, {"name": "execute", "started_at": "2021-08-19T16:05:00.397609Z", "completed_at": "2021-08-19T16:05:00.397613Z"}], "thread_id": "Thread-4", "execution_time": 0.025943994522094727, "message": null, "adapter_response": {}, "unique_id": "test.snowplow_web.not_null_snowplow_web_users_network_userid"}, {"status": "success", "timing": [{"name": "compile", "started_at": "2021-08-19T16:05:00.385258Z", "completed_at": "2021-08-19T16:05:00.397325Z"}, {"name": "execute", "started_at": "2021-08-19T16:05:00.397861Z", "completed_at": "2021-08-19T16:05:00.397865Z"}], "thread_id": "Thread-3", "execution_time": 0.02597808837890625, "message": null, "adapter_response": {}, "unique_id": "test.snowplow_web.not_null_snowplow_web_users_page_views"}, {"status": "success", "timing": [{"name": "compile", "started_at": "2021-08-19T16:05:00.398742Z", "completed_at": "2021-08-19T16:05:00.420070Z"}, {"name": "execute", "started_at": "2021-08-19T16:05:00.420347Z", "completed_at": "2021-08-19T16:05:00.420352Z"}], "thread_id": "Thread-2", "execution_time": 0.022603988647460938, "message": null, "adapter_response": {}, "unique_id": "test.snowplow_web.not_null_snowplow_web_users_sessions"}, {"status": "success", "timing": [{"name": "compile", "started_at": "2021-08-19T16:05:00.398899Z", "completed_at": "2021-08-19T16:05:00.420183Z"}, {"name": "execute", "started_at": "2021-08-19T16:05:00.420567Z", "completed_at": "2021-08-19T16:05:00.420571Z"}], "thread_id": "Thread-1", "execution_time": 0.022493839263916016, "message": null, "adapter_response": {}, "unique_id": "test.snowplow_web.not_null_snowplow_web_users_start_tstamp"}, {"status": "success", "timing": [{"name": "compile", "started_at": "2021-08-19T16:05:00.409674Z", "completed_at": "2021-08-19T16:05:00.420663Z"}, {"name": "execute", "started_at": "2021-08-19T16:05:00.421097Z", "completed_at": "2021-08-19T16:05:00.421101Z"}], "thread_id": "Thread-4", "execution_time": 0.02243208885192871, "message": null, "adapter_response": {}, "unique_id": "test.snowplow_web.unique_snowplow_web_users_domain_userid"}, {"status": "success", "timing": [{"name": "compile", "started_at": "2021-08-19T16:05:00.409763Z", "completed_at": "2021-08-19T16:05:00.743700Z"}, {"name": "execute", "started_at": "2021-08-19T16:05:00.744296Z", "completed_at": "2021-08-19T16:05:00.744323Z"}], "thread_id": "Thread-3", "execution_time": 0.34115099906921387, "message": null, "adapter_response": {}, "unique_id": "test.snowplow_web_integration_tests.dbt_utils_equality_snowplow_web_users_actual_ref_snowplow_web_users_expected_stg_"}], "elapsed_time": 10.567591905593872, "args": {"log_format": "default", "write_json": true, "profiles_dir": "/Users/williamwarner/.dbt", "use_cache": true, "compile": true, "version_check": true, "which": "generate", "rpc_method": "docs.generate"}}